bpb/__init__.py
bpb/bpb.py
bpb/lib/__init__.py
bpb/lib/controller.py
bpb/lib/naver.py
bpb/parser/__init__.py
bpb/parser/markdown.py
bpb/parser/pdf.py
bpb/utils/__init__.py
bpb/utils/progress_bar.py
bpb-1.2.data/scripts/bpb.py
bpb-1.2.dist-info/LICENSE.txt
bpb-1.2.dist-info/METADATA
bpb-1.2.dist-info/WHEEL
bpb-1.2.dist-info/entry_points.txt
bpb-1.2.dist-info/top_level.txt
bpb-1.2.dist-info/RECORD
