Metadata-Version: 2.1
Name: bpb
Version: 1.2
Summary: Naver Blog Auto Posting Bot From Read Markdown File  
Home-page: https://github.com/pjt3591oo/blog_post_bot_cli
Author: Mung
Author-email: pjt3591oo@gmail.com
Maintainer: Mung
Maintainer-email: pjt3591oo@gmail.com
License: MIT
Platform: any
Classifier: Programming Language :: Python :: 3
Classifier: Programming Language :: Python :: 3.2
Classifier: Programming Language :: Python :: 3.3
Classifier: Programming Language :: Python :: 3.4
Classifier: Programming Language :: Python :: 3.5
Classifier: Programming Language :: Python :: 3.6
Requires-Dist: selenium
Requires-Dist: bs4
Requires-Dist: lxml
Requires-Dist: markdown2
Requires-Dist: logger
